corpress/__init__.py
corpress/_modidx.py
corpress/core.py
corpress-1.1.2.dist-info/licenses/LICENSE
corpress-1.1.2.dist-info/METADATA
corpress-1.1.2.dist-info/WHEEL
corpress-1.1.2.dist-info/entry_points.txt
corpress-1.1.2.dist-info/top_level.txt
corpress-1.1.2.dist-info/RECORD
