Metadata-Version: 2.4
Name: corpress
Version: 1.1.2
Summary: Create a text corpus from a WordPress site using the WordPress API.
Home-page: https://github.com/polsci/corpress
Author: polsci
Author-email: polsci@users.noreply.github.com
License: MIT License
Keywords: nbdev jupyter notebook python
Classifier: Development Status :: 4 - Beta
Classifier: Intended Audience :: Developers
Classifier: Natural Language :: English
Classifier: Programming Language :: Python :: 3.8
Classifier: Programming Language :: Python :: 3.9
Classifier: Programming Language :: Python :: 3.10
Classifier: License :: OSI Approved :: MIT License
Requires-Python: >=3.8
License-File: LICENSE
Requires-Dist: requests
Requires-Dist: beautifulsoup4
Requires-Dist: lxml
Requires-Dist: pandas
Requires-Dist: python-slugify
Provides-Extra: dev
Requires-Dist: jupyterlab; extra == "dev"
Requires-Dist: nbdev; extra == "dev"
Requires-Dist: jupyterlab-quarto; extra == "dev"
Requires-Dist: twine; extra == "dev"
Dynamic: author
Dynamic: author-email
Dynamic: classifier
Dynamic: description
Dynamic: description-content-type
Dynamic: home-page
Dynamic: keywords
Dynamic: license
Dynamic: license-file
Dynamic: provides-extra
Dynamic: requires-dist
Dynamic: requires-python
Dynamic: summary
